rac_schemas/__init__.py
rac_schemas/exceptions.py
rac_schemas/schemas/accession.json
rac_schemas/schemas/agent.json
rac_schemas/schemas/aurora_bag.json
rac_schemas/schemas/base.json
rac_schemas/schemas/collection.json
rac_schemas/schemas/copyright_basis.json
rac_schemas/schemas/date.json
rac_schemas/schemas/digitization_bag.json
rac_schemas/schemas/extent.json
rac_schemas/schemas/external_identifier.json
rac_schemas/schemas/group.json
rac_schemas/schemas/language.json
rac_schemas/schemas/legacy_digital_bag.json
rac_schemas/schemas/license_basis.json
rac_schemas/schemas/note.json
rac_schemas/schemas/object.json
rac_schemas/schemas/other_basis.json
rac_schemas/schemas/reference.json
rac_schemas/schemas/rights_basis_information.json
rac_schemas/schemas/rights_granted.json
rac_schemas/schemas/rights_statement.json
rac_schemas/schemas/statute_basis.json
rac_schemas/schemas/term.json
rac_schemas-0.30.dist-info/LICENSE
rac_schemas-0.30.dist-info/METADATA
rac_schemas-0.30.dist-info/WHEEL
rac_schemas-0.30.dist-info/top_level.txt
rac_schemas-0.30.dist-info/RECORD
