Metadata-Version: 2.1
Name: rac-schemas
Version: 0.30
Summary: RAC JSON Schemas and validators
Home-page: http://github.com/RockefellerArchiveCenter/rac_schemas
Author: Rockefeller Archive Center
Author-email: archive@rockarch.org
License: MIT
Platform: UNKNOWN
Classifier: Programming Language :: Python :: 3
Classifier: License :: OSI Approved :: MIT License
Classifier: Operating System :: OS Independent
Requires-Python: >=3.6
License-File: LICENSE
Requires-Dist: jsonschema
